openground/__init__.py
openground/cli.py
openground/config.py
openground/console.py
openground/embeddings.py
openground/ingest.py
openground/query.py
openground/server.py
openground/sources.json
openground/stats.py
openground/update.py
openground/extract/common.py
openground/extract/git.py
openground/extract/sitemap.py
openground/extract/source.py
openground/extract/tests/test_source.py
openground/tests/conftest.py
openground/tests/test_cli.py
openground/tests/test_isolation.py
openground/tests/test_update.py
openground-0.11.1.dist-info/METADATA
openground-0.11.1.dist-info/WHEEL
openground-0.11.1.dist-info/entry_points.txt
openground-0.11.1.dist-info/licenses/LICENSE
openground-0.11.1.dist-info/RECORD
