Metadata-Version: 2.4
Name: openground
Version: 0.11.1
Summary: Ingest official documentation into a local vector database and expose it via MCP for AI coding agents
Project-URL: Homepage, https://github.com/poweroutlet2/openground
Project-URL: Repository, https://github.com/poweroutlet2/openground
Project-URL: Issues, https://github.com/poweroutlet2/openground/issues
License-Expression: MIT
License-File: LICENSE
Keywords: ai,coding-assistant,documentation,embeddings,mcp,vector-database
Classifier: Development Status :: 4 - Beta
Classifier: Environment :: Console
Classifier: Intended Audience :: Developers
Classifier: License :: OSI Approved :: MIT License
Classifier: Operating System :: OS Independent
Classifier: Programming Language :: Python :: 3
Classifier: Programming Language :: Python :: 3.10
Classifier: Programming Language :: Python :: 3.11
Classifier: Programming Language :: Python :: 3.12
Classifier: Programming Language :: Python :: 3.13
Classifier: Topic :: Scientific/Engineering :: Artificial Intelligence
Classifier: Topic :: Software Development :: Documentation
Requires-Python: <3.13,>=3.10
Requires-Dist: aiohttp<4.0.0,>=3.8.0
Requires-Dist: fastmcp<3.0.0,>=2.13.3
Requires-Dist: lancedb<1.0.0,>=0.1.0
Requires-Dist: langchain-text-splitters<2.0.0,>=1.0.0
Requires-Dist: nbformat<6.0.0,>=5.0.0
Requires-Dist: pandas<3.0.0,>=2.3.3
Requires-Dist: pydantic<3.0.0,>=2.0.0
Requires-Dist: rich<15.0.0,>=14.0.0
Requires-Dist: sentence-transformers<6.0.0,>=5.0.0
Requires-Dist: torch<3.0.0,>=2.0.0
Requires-Dist: tqdm>=4.60.0
Requires-Dist: trafilatura<3.0.0,>=2.0.0
Requires-Dist: typer<1.0.0,>=0.9.0
Provides-Extra: fastembed-cpu
Requires-Dist: fastembed<1.0.0,>=0.2.0; extra == 'fastembed-cpu'
Provides-Extra: fastembed-gpu
Requires-Dist: fastembed-gpu<1.0.0,>=0.2.0; extra == 'fastembed-gpu'
